cdk8s_valheim/__init__.py
cdk8s_valheim/py.typed
cdk8s_valheim/_jsii/__init__.py
cdk8s_valheim/_jsii/cdk8s-valheim@0.0.270.jsii.tgz
cdk8s_valheim-0.0.270.dist-info/LICENSE
cdk8s_valheim-0.0.270.dist-info/METADATA
cdk8s_valheim-0.0.270.dist-info/WHEEL
cdk8s_valheim-0.0.270.dist-info/top_level.txt
cdk8s_valheim-0.0.270.dist-info/RECORD
