Metadata-Version: 2.1
Name: cdk8s-valheim
Version: 0.0.270
Summary: A package that vends a Valheim server chart.
Home-page: https://github.com/awlsring/cdk8s-valheim.git
Author: awlsring<mattcanemail@gmail.com>
License: Apache-2.0
Project-URL: Source, https://github.com/awlsring/cdk8s-valheim.git
Classifier: Intended Audience :: Developers
Classifier: Operating System :: OS Independent
Classifier: Programming Language :: JavaScript
Classifier: Programming Language :: Python :: 3 :: Only
Classifier: Programming Language :: Python :: 3.8
Classifier: Programming Language :: Python :: 3.9
Classifier: Programming Language :: Python :: 3.10
Classifier: Programming Language :: Python :: 3.11
Classifier: Typing :: Typed
Classifier: Development Status :: 5 - Production/Stable
Classifier: License :: OSI Approved
Requires-Python: ~=3.8
License-File: LICENSE
Requires-Dist: cdk8s-plus-26 ==2.2.2
Requires-Dist: cdk8s <3.0.0,>=2.7.36
Requires-Dist: constructs <11.0.0,>=10.1.281
Requires-Dist: jsii <2.0.0,>=1.93.0
Requires-Dist: publication >=0.0.3
Requires-Dist: typeguard ~=2.13.3
